Lab_04/Ejercicio 04/Lab04.V
// Modulos Ejercicios 04
// Jonathan Menendez
// 18023
module Gates_Level_01(input wire inA, inB, inC, inD, output wire Y);

    // Declaracion de variables

    wire N1, N2, N3, N4;                  // Not del circuito
    wire A1, A2, A3, A4, A5, A6, A7, A8;  // And del circuito

    //Declaracion de compuertas

    not NA (N1,   inA); // A not
    not NB (N2,   inB); // B not
    not NC (N3,   inC); // C not
    not ND (N4,   inD); // D not
    and AA (A1,   N1, N2, N3, N4); // Entradas del And
    and AB (A2,   N1, N2, inC, inD); // Entradas del And
    and AC (A3,   N1, inB, N3, inD); // Entradas del And
    and AD (A4,   N1, inB, inC, N4); // Entradas del And
    and AE (A5,   inA, inB, N3, N4); // Entradas del And
    and AF (A6,   inA, inB, inC, inD); // Entradas del And
    and AG (A7,   inA, N2, N3, inD); // Entradas del And
    and AG (A8,   inA, N2, inC, N4); // Entradas del And
    or O0 (Y,    A1, A2, A3, A4, A5, A6, A7, A8); //Las 8 entradas del Or_1

endmodule //Modulo 01

module Gates_Level_02(input wire inA, inB, inC, output wire Y);

    // Declaracion de variables

    wire N1;                  // Not

    //Declaracion de compuertas

    not NB (N1,   inB); // B not
    and AA (Y,    N1);

endmodule //Modulo 02

module Gates_Level_03(input wire inA, inB, inC, output wire Y);

    // Declaracion de variables

    wire N2;                  // Not
    wire A1, A2;

    //Declaracion de compuertas

    not NB (N2,     inB); // B not
    and AA (A1,     N2);
    and AB (A2,     inB, inC);
    or O0 (Y,      A1, A2);

endmodule //Modulo 03

module Gates_Level_04(input wire inA, inB, inC, output wire Y);

    // Declaracion de variables(gl)

    wire N1, N3;                  // Not
    wire A1, A2;

    //Declaracion de compuertas

    not NA (N1,     inA); // B not
    not NC (N3,     inC);
    and AA (A1,     N1, N3);
    and AB (A2,     inB);
    or O0 (Y,      A1, A2);

endmodule //Modulo 04

module Logic_Operator_01(input wire inA, inB, inC, output wire Y);

    //Declaracion de variables

    assign Y = (~inA & ~inC) | (~inB & ~inC) | (inA & inC);

endmodule //Modulo 05

module Logic_Operator_02(input wire inA, inB, inC, inD, output wire Y);

    //Declaracion de variables
    assign Y = (inA & inB) | (inA & inC) | (~inB & ~inD);

endmodule //Modulo 06

module Logic_Operator_03(input wire inA, inB, inC, inD, output wire Y);

    //Declaracion de variables
    assign Y = (~inB & ~inC & ~inD) | (inA & ~inD) | (inA & ~inB) | (inA & ~inC);

endmodule //Modulo 07 code by Logic Operators

module Logic_Operator_04(input wire inA, inB, inC, inD, output wire Y);

    //Declaracion de variables de modo logico
    assign Y = (inB) | (~inC & inD) | (inA & inD);

endmodule //Modulo 08

Lab_04/Ejercicio 04/Lab04_tb.v

// Modulo de llamada Digital_Modelling.v
//TestBench (tb)

module testbench();

//Variables para todos los modulos
reg p1, p2, p3, p4, p5, p6, p7, p8, p9, p10, p11, p12, p13; // Una variable por input gates
reg a1, a2, a3, a4, a5, a6, a7, a8, a9, a10, a11, a12, a13, a14, a15; // Una variable por input logic
wire out1, out2, out3, out4, out5, out6, out7, out8;

Gates_Level_01 G1(p1, p2, p3, p4, out1); //Configuracion del modulo Gates_Level_01
Gates_Level_02 G2(p5, p6, p7, out2); // Configuracion para modulo 02
Gates_Level_03 G3(p8, p9, p10, out3); // Configuracion para modulo 03
Gates_Level_04 G4(p11, p12, p13, out4); // Configuracion para modulo 04
Logic_Operator_01 L1(a1, a2, a3, out5);
Logic_Operator_02 L2(a4, a5, a6, a7, out6);
Logic_Operator_03 L3(a8, a9, a10, a11, out7);
Logic_Operator_04 L4(a12, a13, a14, a15, out8);
// Llamada a los archivor .v

initial begin // Tabla de verdad modulo 01
  $display("A B C D | Y");
  $display("--------|--");
  $monitor("%b %b %b %b | %b", p1, p2, p3, p4, out1);
   p1 = 0; p2 = 0; p3 = 0; p4 = 0;
#1 p1 = 0; p2 = 0; p3 = 0; p4 = 1;
#1 p1 = 0; p2 = 0; p3 = 1; p4 = 0;
#1 p1 = 0; p2 = 0; p3 = 1; p4 = 1;
#1 p1 = 0; p2 = 1; p3 = 0; p4 = 0;
#1 p1 = 0; p2 = 1; p3 = 0; p4 = 1;
#1 p1 = 0; p2 = 1; p3 = 1; p4 = 0;
#1 p1 = 0; p2 = 1; p3 = 1; p4 = 1;
#1 p1 = 1; p2 = 0; p3 = 0; p4 = 0;
#1 p1 = 1; p2 = 0; p3 = 0; p4 = 1;
#1 p1 = 1; p2 = 0; p3 = 1; p4 = 0;
#1 p1 = 1; p2 = 0; p3 = 1; p4 = 1;
#1 p1 = 1; p2 = 1; p3 = 0; p4 = 0;
#1 p1 = 1; p2 = 1; p3 = 0; p4 = 1;
#1 p1 = 1; p2 = 1; p3 = 1; p4 = 0;
#1 p1 = 1; p2 = 1; p3 = 1; p4 = 1;
end // Tiempo 15

initial begin // Tabla de verdad modulo 02
 #16
 $display("\n");
 $display("A B C | Y");
 $display("------|--");
 $monitor("%b %b %b | %b", p5, p6, p7, out2);
   p5 = 0; p6 = 0; p7 = 0;
#1 p5 = 0; p6 = 0; p7 = 1;
#1 p5 = 0; p6 = 1; p7 = 0;
#1 p5 = 0; p6 = 1; p7 = 1;
#1 p5 = 1; p6 = 0; p7 = 0;
#1 p5 = 1; p6 = 0; p7 = 1;
#1 p5 = 1; p6 = 1; p7 = 0;
#1 p5 = 1; p6 = 1; p7 = 1;
end // Termina en tiempo 23

initial begin// Tabla de verdad modulo 3
 #24
 $display("\n");
 $display("A B C | Y");
 $display("------|--");
 $monitor("%b %b %b | %b", p8, p9, p10, out3);
   p8 = 0; p9 = 0; p10 = 0;
#1 p8 = 0; p9 = 0; p10 = 1;
#1 p8 = 0; p9 = 1; p10 = 0;
#1 p8 = 0; p9 = 1; p10 = 1;
#1 p8 = 1; p9 = 0; p10 = 0;
#1 p8 = 1; p9 = 0; p10 = 1;
#1 p8 = 1; p9 = 1; p10 = 0;
#1 p8 = 1; p9 = 1; p10 = 1;
end // Termina en tiempo 32

initial begin// Display de la tabla de verdad modulo 4
 #32
 $display("\n");
 $display("A B C | Y");
 $display("------|--");
 $monitor("%b %b %b | %b", p11, p12, p13, out4);
   p11 = 0; p12 = 0; p13 = 0;
#1 p11 = 0; p12 = 0; p13 = 1;
#1 p11 = 0; p12 = 1; p13 = 0;
#1 p11 = 0; p12 = 1; p13 = 1;
#1 p11 = 1; p12 = 0; p13 = 0;
#1 p11 = 1; p12 = 0; p13 = 1;
#1 p11 = 1; p12 = 1; p13 = 0;
#1 p11 = 1; p12 = 1; p13 = 1;
end // Termina en tiempo 39

initial begin
#40
$display("A B C | Y");
$display("------|--");
$monitor("%b %b %b | %b", a1, a2, a3, out5);
   a1 = 0; a2 = 0; a3 = 0;
#1 a1 = 0; a2 = 0; a3 = 1;
#1 a1 = 0; a2 = 1; a3 = 0;
#1 a1 = 0; a2 = 1; a3 = 1;
#1 a1 = 1; a2 = 0; a3 = 0;
#1 a1 = 1; a2 = 0; a3 = 1;
#1 a1 = 1; a2 = 1; a3 = 0;
#1 a1 = 1; a2 = 1; a3 = 1;
end //Termina en tiempo 47

initial begin
#48
$display("A B C D| Y");
$display("-------|--");
$monitor("%b %b %b %b | %b", a4, a5, a6, a7, out6);
   a4 = 0; a5 = 0; a6 = 0; a7 = 0;
#1 a4 = 0; a5 = 0; a6 = 0; a7 = 1;
#1 a4 = 0; a5 = 0; a6 = 1; a7 = 0;
#1 a4 = 0; a5 = 0; a6 = 1; a7 = 1;
#1 a4 = 0; a5 = 1; a6 = 0; a7 = 0;
#1 a4 = 0; a5 = 1; a6 = 0; a7 = 1;
#1 a4 = 0; a5 = 1; a6 = 1; a7 = 0;
#1 a4 = 0; a5 = 1; a6 = 1; a7 = 1;
#1 a4 = 1; a5 = 0; a6 = 0; a7 = 0;
#1 a4 = 1; a5 = 0; a6 = 0; a7 = 1;
#1 a4 = 1; a5 = 0; a6 = 1; a7 = 0;
#1 a4 = 1; a5 = 0; a6 = 1; a7 = 1;
#1 a4 = 1; a5 = 1; a6 = 0; a7 = 0;
#1 a4 = 1; a5 = 1; a6 = 0; a7 = 1;
#1 a4 = 1; a5 = 1; a6 = 1; a7 = 0;
#1 a4 = 1; a5 = 1; a6 = 1; a7 = 1;
end //Termina en tiempo 63

initial begin
#64
$display("A B C D| Y");
$display("-------|--");
$monitor("%b %b %b %b | %b", a8, a9, a10, a11, out7);
   a8 = 0; a9 = 0; a10 = 0; a11 = 0;
#1 a8 = 0; a9 = 0; a10 = 0; a11 = 1;
#1 a8 = 0; a9 = 0; a10 = 1; a11 = 0;
#1 a8 = 0; a9 = 0; a10 = 1; a11 = 1;
#1 a8 = 0; a9 = 1; a10 = 0; a11 = 0;
#1 a8 = 0; a9 = 1; a10 = 0; a11 = 1;
#1 a8 = 0; a9 = 1; a10 = 1; a11 = 0;
#1 a8 = 0; a9 = 1; a10 = 1; a11 = 1;
#1 a8 = 1; a9 = 0; a10 = 0; a11 = 0;
#1 a8 = 1; a9 = 0; a10 = 0; a11 = 1;
#1 a8 = 1; a9 = 0; a10 = 1; a11 = 0;
#1 a8 = 1; a9 = 0; a10 = 1; a11 = 1;
#1 a8 = 1; a9 = 1; a10 = 0; a11 = 0;
#1 a8 = 1; a9 = 1; a10 = 0; a11 = 1;
#1 a8 = 1; a9 = 1; a10 = 1; a11 = 0;
#1 a8 = 1; a9 = 1; a10 = 1; a11 = 1;
end //Termina en tiempo 79

initial begin
#80
$display("A B C D| Y");
$display("-------|--");
$monitor("%b %b %b %b | %b", a12, a13, a14, a15, out8);
   a12 = 0; a13 = 0; a14 = 0; a15 = 0;
#1 a12 = 0; a13 = 0; a14 = 0; a15 = 1;
#1 a12 = 0; a13 = 0; a14 = 1; a15 = 0;
#1 a12 = 0; a13 = 0; a14 = 1; a15 = 1;
#1 a12 = 0; a13 = 1; a14 = 0; a15 = 0;
#1 a12 = 0; a13 = 1; a14 = 0; a15 = 1;
#1 a12 = 0; a13 = 1; a14 = 1; a15 = 0;
#1 a12 = 0; a13 = 1; a14 = 1; a15 = 1;
#1 a12 = 1; a13 = 0; a14 = 0; a15 = 0;
#1 a12 = 1; a13 = 0; a14 = 0; a15 = 1;
#1 a12 = 1; a13 = 0; a14 = 1; a15 = 0;
#1 a12 = 1; a13 = 0; a14 = 1; a15 = 1;
#1 a12 = 1; a13 = 1; a14 = 0; a15 = 0;
#1 a12 = 1; a13 = 1; a14 = 0; a15 = 1;
#1 a12 = 1; a13 = 1; a14 = 1; a15 = 0;
#1 a12 = 1; a13 = 1; a14 = 1; a15 = 1;
end //Termina en tiempo 95

// Iniciar la funcion del GtkWave
initial // modulo final
  #96 $finish;

initial begin
$dumpfile("Digital_Modelling_tb.vcd");
$dumpvars(0, testbench);
end

endmodule

Lab_04/Ejercicio 04/Digital_Modelling_tb.vcd
$date
	Sun Aug 09 15:50:13 2020
$end
$version
	Icarus Verilog
$end
$timescale
	1ps
$end
$scope module testbench $end
$var wire 1 ! out8 $end
$var wire 1 " out7 $end
$var wire 1 # out6 $end
$var wire 1 $ out5 $end
$var wire 1 % out4 $end
$var wire 1 & out3 $end
$var wire 1 ' out2 $end
$var wire 1 ( out1 $end
$var reg 1 ) a1 $end
$var reg 1 * a10 $end
$var reg 1 + a11 $end
$var reg 1 , a12 $end
$var reg 1 - a13 $end
$var reg 1 . a14 $end
$var reg 1 / a15 $end
$var reg 1 0 a2 $end
$var reg 1 1 a3 $end
$var reg 1 2 a4 $end
$var reg 1 3 a5 $end
$var reg 1 4 a6 $end
$var reg 1 5 a7 $end
$var reg 1 6 a8 $end
$var reg 1 7 a9 $end
$var reg 1 8 p1 $end
$var reg 1 9 p10 $end
$var reg 1 : p11 $end
$var reg 1 ; p12 $end
$var reg 1 < p13 $end
$var reg 1 = p2 $end
$var reg 1 > p3 $end
$var reg 1 ? p4 $end
$var reg 1 @ p5 $end
$var reg 1 A p6 $end
$var reg 1 B p7 $end
$var reg 1 C p8 $end
$var reg 1 D p9 $end
$scope module G1 $end
$var wire 1 E A1 $end
$var wire 1 F A2 $end
$var wire 1 G A3 $end
$var wire 1 H A4 $end
$var wire 1 I A5 $end
$var wire 1 J A6 $end
$var wire 1 K A7 $end
$var wire 1 L A8 $end
$var wire 1 M N1 $end
$var wire 1 N N2 $end
$var wire 1 O N3 $end
$var wire 1 P N4 $end
$var wire 1 ( Y $end
$var wire 1 8 inA $end
$var wire 1 = inB $end
$var wire 1 > inC $end
$var wire 1 ? inD $end
$upscope $end
$scope module G2 $end
$var wire 1 Q N1 $end
$var wire 1 ' Y $end
$var wire 1 @ inA $end
$var wire 1 A inB $end
$var wire 1 B inC $end
$upscope $end
$scope module G3 $end
$var wire 1 R A1 $end
$var wire 1 S A2 $end
$var wire 1 T N2 $end
$var wire 1 & Y $end
$var wire 1 C inA $end
$var wire 1 D inB $end
$var wire 1 9 inC $end
$upscope $end
$scope module G4 $end
$var wire 1 U A1 $end
$var wire 1 V A2 $end
$var wire 1 W N1 $end
$var wire 1 X N3 $end
$var wire 1 % Y $end
$var wire 1 : inA $end
$var wire 1 ; inB $end
$var wire 1 < inC $end
$upscope $end
$scope module L1 $end
$var wire 1 $ Y $end
$var wire 1 ) inA $end
$var wire 1 0 inB $end
$var wire 1 1 inC $end
$upscope $end
$scope module L2 $end
$var wire 1 # Y $end
$var wire 1 2 inA $end
$var wire 1 3 inB $end
$var wire 1 4 inC $end
$var wire 1 5 inD $end
$upscope $end
$scope module L3 $end
$var wire 1 " Y $end
$var wire 1 6 inA $end
$var wire 1 7 inB $end
$var wire 1 * inC $end
$var wire 1 + inD $end
$upscope $end
$scope module L4 $end
$var wire 1 ! Y $end
$var wire 1 , inA $end
$var wire 1 - inB $end
$var wire 1 . inC $end
$var wire 1 / inD $end
$upscope $end
$upscope $end
$enddefinitions $end
#0
$dumpvars
xX
xW
xV
xU
xT
xS
xR
xQ
1P
1O
1N
1M
0L
0K
0J
0I
0H
0G
0F
1E
xD
xC
xB
xA
x@
0?
0>
0=
x<
x;
x:
x9
08
x7
x6
x5
x4
x3
x2
x1
x0
x/
x.
x-
x,
x+
x*
x)
1(
x'
x&
x%
x$
x#
x"
x!
$end
#1
0(
0E
0P
1?
#2
1P
0O
0?
1>
#3
1(
0P
1F
1?
#4
0(
1P
1O
0F
0N
0?
0>
1=
#5
1(
0P
1G
1?
#6
1(
1H
1P
0G
0O
0?
1>
#7
0(
0H
0P
1?
#8
1P
1O
1N
0M
0?
0>
0=
18
#9
1(
0P
1K
1?
#10
1(
1L
1P
0K
0O
0?
1>
#11
0(
0L
0P
1?
#12
1(
1I
1P
1O
0N
0?
0>
1=
#13
0(
0I
0P
1?
#14
1P
0O
0?
1>
#15
1(
0P
1J
1?
#16
1'
1Q
0B
0A
0@
#17
1B
#18
0'
0Q
0B
1A
#19
1B
#20
1'
1Q
0B
0A
1@
#21
1B
#22
0'
0Q
0B
1A
#23
1B
#24
1&
1R
1T
0S
09
0D
0C
#25
19
#26
0&
0R
0T
09
1D
#27
1&
1S
19
#28
1R
1&
1T
0S
09
0D
1C
#29
19
#30
0&
0R
0T
09
1D
#31
1&
1S
19
#32
1%
1U
1X
0V
1W
0<
0;
0:
#33
0%
0U
0X
1<
#34
1U
1%
1X
1V
0<
1;
#35
0U
0X
1<
#36
0%
1X
0V
0W
0<
0;
1:
#37
0X
1<
#38
1%
1X
1V
0<
1;
#39
0X
1<
#40
1$
01
00
0)
#41
0$
11
#42
1$
01
10
#43
0$
11
#44
1$
01
00
1)
#45
11
#46
0$
01
10
#47
1$
11
#48
1#
05
04
03
02
#49
0#
15
#50
1#
05
14
#51
0#
15
#52
05
04
13
#53
15
#54
05
14
#55
15
#56
1#
05
04
03
12
#57
0#
15
#58
1#
05
14
#59
15
#60
05
04
13
#61
15
#62
05
14
#63
15
#64
1"
0+
0*
07
06
#65
0"
1+
#66
0+
1*
#67
1+
#68
0+
0*
17
#69
1+
#70
0+
1*
#71
1+
#72
1"
0+
0*
07
16
#73
1+
#74
0+
1*
#75
1+
#76
0+
0*
17
#77
1+
#78
1"
0+
1*
#79
0"
1+
#80
0!
0/
0.
0-
0,
#81
1!
1/
#82
0!
0/
1.
#83
1/
#84
1!
0/
0.
1-
#85
1/
#86
0/
1.
#87
1/
#88
0!
0/
0.
0-
1,
#89
1!
1/
#90
0!
0/
1.
#91
1!
1/
#92
0/
0.
1-
#93
1/
#94
0/
1.
#95
1/
